php_framework_scaffolder/__init__.py
php_framework_scaffolder/cli.py
php_framework_scaffolder/frameworks/__init__.py
php_framework_scaffolder/frameworks/base.py
php_framework_scaffolder/frameworks/cakephp.py
php_framework_scaffolder/frameworks/codeigniter.py
php_framework_scaffolder/frameworks/drupal.py
php_framework_scaffolder/frameworks/drush.py
php_framework_scaffolder/frameworks/factory.py
php_framework_scaffolder/frameworks/fastroute.py
php_framework_scaffolder/frameworks/fatfree.py
php_framework_scaffolder/frameworks/fuel.py
php_framework_scaffolder/frameworks/laminas.py
php_framework_scaffolder/frameworks/laravel.py
php_framework_scaffolder/frameworks/na.py
php_framework_scaffolder/frameworks/phalcon.py
php_framework_scaffolder/frameworks/phpixie.py
php_framework_scaffolder/frameworks/popphp.py
php_framework_scaffolder/frameworks/slim.py
php_framework_scaffolder/frameworks/symfony.py
php_framework_scaffolder/frameworks/thinkphp.py
php_framework_scaffolder/frameworks/yii.py
php_framework_scaffolder/frameworks/zendframework.py
php_framework_scaffolder/models/progress.py
php_framework_scaffolder/templates/cakephp/.dockerignore
php_framework_scaffolder/templates/cakephp/Dockerfile
php_framework_scaffolder/templates/cakephp/README.md
php_framework_scaffolder/templates/cakephp/app.env
php_framework_scaffolder/templates/cakephp/app.example.env
php_framework_scaffolder/templates/cakephp/coverage-collector.php
php_framework_scaffolder/templates/cakephp/docker-compose.yaml
php_framework_scaffolder/templates/cakephp/mysql.env
php_framework_scaffolder/templates/cakephp/mysql.example.env
php_framework_scaffolder/templates/cakephp/postgres.env
php_framework_scaffolder/templates/cakephp/postgres.example.env
php_framework_scaffolder/templates/codeigniter/.dockerignore
php_framework_scaffolder/templates/codeigniter/Dockerfile
php_framework_scaffolder/templates/codeigniter/README.md
php_framework_scaffolder/templates/codeigniter/app.env
php_framework_scaffolder-0.1.123.dist-info/METADATA
php_framework_scaffolder-0.1.123.dist-info/WHEEL
php_framework_scaffolder-0.1.123.dist-info/entry_points.txt
php_framework_scaffolder-0.1.123.dist-info/top_level.txt
php_framework_scaffolder-0.1.123.dist-info/RECORD
